{
  "caps": [
    {
      "cap_id": "CAP1",
      "cap_type": "Diagnosis",
      "content_source": "clinician",
      "modality": "assessment",
      "canonical_concept": "MCL strain",
      "verification_status": "confirmed",
      "clinical_status": "active",
      "temporality": "current",
      "proposition_text": "The patient has an MCL strain.",
      "evidence": [
        {
          "turn_id": "S22",
          "turn_speaker": "note",
          "span_text": "Right knee MCL strain.",
          "char_start": 0,
          "char_end": 22
        }
      ],
      "assertion": "present",
      "visit_state": "active",
      "linked_problem": null
    },
    {
      "cap_id": "CAP2",
      "cap_type": "Diagnosis",
      "content_source": "clinician",
      "modality": "assessment",
      "canonical_concept": "Hypertension",
      "verification_status": "confirmed",
      "clinical_status": "active",
      "temporality": "current",
      "proposition_text": "The clinician assesses hypertension.",
      "evidence": [
        {
          "turn_id": "S24",
          "turn_speaker": "note",
          "span_text": "Hypertension.",
          "char_start": 0,
          "char_end": 13
        }
      ],
      "assertion": "present",
      "visit_state": "active",
      "linked_problem": null
    },
    {
      "cap_id": "CAP3",
      "cap_type": "Problem",
      "content_source": "clinician",
      "modality": "unknown",
      "canonical_concept": "MRI",
      "verification_status": "confirmed",
      "clinical_status": "active",
      "temporality": "future",
      "proposition_text": "The clinician recommends obtaining an MRI of the right knee.",
      "evidence": [
        {
          "turn_id": "S30",
          "turn_speaker": "note",
          "span_text": "The patient will follow up with me in 2 weeks to review his MRI results.",
          "char_start": 0,
          "char_end": 72
        }
      ],
      "assertion": "present",
      "visit_state": "active",
      "linked_problem": null
    },
    {
      "cap_id": "CAP4",
      "cap_type": "Problem",
      "content_source": "clinician",
      "modality": "unknown",
      "canonical_concept": "referral",
      "verification_status": "confirmed",
      "clinical_status": "active",
      "temporality": "future",
      "proposition_text": "The clinician recommends a referral for a nutritionist.",
      "evidence": [
        {
          "turn_id": "S27",
          "turn_speaker": "note",
          "span_text": "In terms of his diabetes, he was advised to start logging his blood sugars daily and to avoid eating large amounts of strawberries. He will also be provided with a referral for a consult with a nutritionist.",
          "char_start": 0,
          "char_end": 207
        }
      ],
      "assertion": "present",
      "visit_state": "active",
      "linked_problem": null
    },
    {
      "cap_id": "CAP5",
      "cap_type": "Symptom",
      "content_source": "clinician",
      "modality": "assessment",
      "canonical_concept": "swelling",
      "verification_status": "confirmed",
      "clinical_status": "active",
      "temporality": "current",
      "proposition_text": "The clinician assesses swelling in the knee.",
      "evidence": [
        {
          "turn_id": "S3",
          "turn_speaker": "note",
          "span_text": "Matthew Allen is a pleasant 40-year-old male who presents to the clinic today for the evaluation of right knee pain. The onset of his pain began yesterday after he went up for a rebound while playing basketball and felt a pop in his knee. He states that he experienced swelling and difficulty with ambulation following this incident. He locates his pain today to the medial aspect of his knee. His pain is described as aching and is rated at 4 out of 10. In terms of his swelling, he states that this has improved some. He is also able to weight-bear, but he finds that he is favoring his left leg while doing so. His tried treatments include Tylenol with some relief as well as rest.",
          "char_start": 0,
          "char_end": 684
        }
      ],
      "assertion": "present",
      "visit_state": "active",
      "linked_problem": null
    },
    {
      "cap_id": "CAP6",
      "cap_type": "Symptom",
      "content_source": "clinician",
      "modality": "assessment",
      "canonical_concept": "pain",
      "verification_status": "confirmed",
      "clinical_status": "active",
      "temporality": "current",
      "proposition_text": "The clinician assesses pain at a 4/10.",
      "evidence": [
        {
          "turn_id": "S1",
          "turn_speaker": "note",
          "span_text": "Right knee pain",
          "char_start": 0,
          "char_end": 15
        }
      ],
      "assertion": "present",
      "visit_state": "active",
      "linked_problem": null
    },
    {
      "cap_id": "CAP7",
      "cap_type": "Problem",
      "content_source": "clinician",
      "modality": "assessment",
      "canonical_concept": "hypertension",
      "verification_status": "confirmed",
      "clinical_status": "active",
      "temporality": "current",
      "proposition_text": "The clinician assesses a history of hypertension.",
      "evidence": [
        {
          "turn_id": "S6",
          "turn_speaker": "note",
          "span_text": "Patient reports history of hypertension and diabetes.",
          "char_start": 0,
          "char_end": 53
        }
      ],
      "assertion": "present",
      "visit_state": "active",
      "linked_problem": null
    },
    {
      "cap_id": "CAP8",
      "cap_type": "Problem",
      "content_source": "clinician",
      "modality": "assessment",
      "canonical_concept": "diabetes",
      "verification_status": "confirmed",
      "clinical_status": "active",
      "temporality": "current",
      "proposition_text": "The clinician assesses a history of diabetes.",
      "evidence": [
        {
          "turn_id": "S6",
          "turn_speaker": "note",
          "span_text": "Patient reports history of hypertension and diabetes.",
          "char_start": 0,
          "char_end": 53
        }
      ],
      "assertion": "present",
      "visit_state": "active",
      "linked_problem": null
    },
    {
      "cap_id": "CAP9",
      "cap_type": "Problem",
      "content_source": "clinician",
      "modality": "unknown",
      "canonical_concept": "Tylenol",
      "verification_status": "confirmed",
      "clinical_status": "active",
      "temporality": "current",
      "proposition_text": "The clinician recommends Tylenol for pain relief.",
      "evidence": [
        {
          "turn_id": "S26",
          "turn_speaker": "note",
          "span_text": "After reviewing the patient's examination and radiographic findings today, I had a lengthy discussion with the patient in regards to his current symptoms. I have recommended that we obtain an MRI of the right knee to further evaluate for a possible MCL tear. In the meantime, he will continue with Tylenol for pain relief. I have also prescribed him meloxicam 15 mg for pain and swelling. He will be placed into a knee immobilizer and has been advised to remain non weight-bearing for the next couple of weeks.",
          "char_start": 0,
          "char_end": 510
        }
      ],
      "assertion": "present",
      "visit_state": "active",
      "linked_problem": null
    },
    {
      "cap_id": "CAP10",
      "cap_type": "Symptom",
      "content_source": "clinician",
      "modality": "assessment",
      "canonical_concept": "knee pain",
      "verification_status": "confirmed",
      "clinical_status": "active",
      "temporality": "current",
      "proposition_text": "The clinician assesses right knee pain.",
      "evidence": [
        {
          "turn_id": "S1",
          "turn_speaker": "note",
          "span_text": "Right knee pain",
          "char_start": 0,
          "char_end": 15
        }
      ],
      "assertion": "present",
      "visit_state": "active",
      "linked_problem": null
    },
    {
      "cap_id": "CAP11",
      "cap_type": "Problem",
      "content_source": "clinician",
      "modality": "unknown",
      "canonical_concept": "knee immobilizer",
      "verification_status": "confirmed",
      "clinical_status": "active",
      "temporality": "current",
      "proposition_text": "The clinician orders a knee immobilizer.",
      "evidence": [
        {
          "turn_id": "S26",
          "turn_speaker": "note",
          "span_text": "After reviewing the patient's examination and radiographic findings today, I had a lengthy discussion with the patient in regards to his current symptoms. I have recommended that we obtain an MRI of the right knee to further evaluate for a possible MCL tear. In the meantime, he will continue with Tylenol for pain relief. I have also prescribed him meloxicam 15 mg for pain and swelling. He will be placed into a knee immobilizer and has been advised to remain non weight-bearing for the next couple of weeks.",
          "char_start": 0,
          "char_end": 510
        }
      ],
      "assertion": "present",
      "visit_state": "active",
      "linked_problem": null
    },
    {
      "cap_id": "CAP12",
      "cap_type": "Problem",
      "content_source": "clinician",
      "modality": "unknown",
      "canonical_concept": "non weight-bearing",
      "verification_status": "confirmed",
      "clinical_status": "active",
      "temporality": "current",
      "proposition_text": "The clinician advises non weight-bearing.",
      "evidence": [
        {
          "turn_id": "S26",
          "turn_speaker": "note",
          "span_text": "After reviewing the patient's examination and radiographic findings today, I had a lengthy discussion with the patient in regards to his current symptoms. I have recommended that we obtain an MRI of the right knee to further evaluate for a possible MCL tear. In the meantime, he will continue with Tylenol for pain relief. I have also prescribed him meloxicam 15 mg for pain and swelling. He will be placed into a knee immobilizer and has been advised to remain non weight-bearing for the next couple of weeks.",
          "char_start": 0,
          "char_end": 510
        }
      ],
      "assertion": "present",
      "visit_state": "active",
      "linked_problem": null
    },
    {
      "cap_id": "CAP13",
      "cap_type": "Problem",
      "content_source": "clinician",
      "modality": "assessment",
      "canonical_concept": "diabetes",
      "verification_status": "confirmed",
      "clinical_status": "active",
      "temporality": "current",
      "proposition_text": "The patient has diabetes.",
      "evidence": [
        {
          "turn_id": "S23",
          "turn_speaker": "note",
          "span_text": "Diabetes.",
          "char_start": 0,
          "char_end": 9
        }
      ],
      "assertion": "present",
      "visit_state": "active",
      "linked_problem": null
    },
    {
      "cap_id": "CAP14",
      "cap_type": "Symptom",
      "content_source": "clinician",
      "modality": "assessment",
      "canonical_concept": "pain",
      "verification_status": "confirmed",
      "clinical_status": "active",
      "temporality": "current",
      "proposition_text": "The clinician assesses pain.",
      "evidence": [
        {
          "turn_id": "S26",
          "turn_speaker": "note",
          "span_text": "After reviewing the patient's examination and radiographic findings today, I had a lengthy discussion with the patient in regards to his current symptoms. I have recommended that we obtain an MRI of the right knee to further evaluate for a possible MCL tear. In the meantime, he will continue with Tylenol for pain relief. I have also prescribed him meloxicam 15 mg for pain and swelling. He will be placed into a knee immobilizer and has been advised to remain non weight-bearing for the next couple of weeks.",
          "char_start": 0,
          "char_end": 510
        }
      ],
      "assertion": "present",
      "visit_state": "active",
      "linked_problem": null
    },
    {
      "cap_id": "CAP15",
      "cap_type": "ExamFinding",
      "content_source": "clinician",
      "modality": "assessment",
      "canonical_concept": "medial knee pain",
      "verification_status": "confirmed",
      "clinical_status": "active",
      "temporality": "current",
      "proposition_text": "The clinician notes pain over the medial aspect of the right knee.",
      "evidence": [
        {
          "turn_id": "S22",
          "turn_speaker": "note",
          "span_text": "Right knee MCL strain.",
          "char_start": 0,
          "char_end": 22
        }
      ],
      "assertion": "present",
      "visit_state": "active",
      "linked_problem": null
    },
    {
      "cap_id": "CAP16",
      "cap_type": "ExamFinding",
      "content_source": "clinician",
      "modality": "assessment",
      "canonical_concept": "knee pain",
      "verification_status": "confirmed",
      "clinical_status": "active",
      "temporality": "current",
      "proposition_text": "The patient experiences pain in the right knee.",
      "evidence": [
        {
          "turn_id": "S22",
          "turn_speaker": "note",
          "span_text": "Right knee MCL strain.",
          "char_start": 0,
          "char_end": 22
        }
      ],
      "assertion": "present",
      "visit_state": "active",
      "linked_problem": null
    },
    {
      "cap_id": "CAP17",
      "cap_type": "ExamFinding",
      "content_source": "clinician",
      "modality": "assessment",
      "canonical_concept": "knee edema",
      "verification_status": "confirmed",
      "clinical_status": "active",
      "temporality": "current",
      "proposition_text": "The patient exhibits edema in the right knee.",
      "evidence": [
        {
          "turn_id": "S22",
          "turn_speaker": "note",
          "span_text": "Right knee MCL strain.",
          "char_start": 0,
          "char_end": 22
        }
      ],
      "assertion": "present",
      "visit_state": "active",
      "linked_problem": null
    },
    {
      "cap_id": "CAP18",
      "cap_type": "ExamFinding",
      "content_source": "clinician",
      "modality": "assessment",
      "canonical_concept": "knee ecchymosis",
      "verification_status": "confirmed",
      "clinical_status": "active",
      "temporality": "current",
      "proposition_text": "The patient demonstrates ecchymosis in the right knee.",
      "evidence": [
        {
          "turn_id": "S22",
          "turn_speaker": "note",
          "span_text": "Right knee MCL strain.",
          "char_start": 0,
          "char_end": 22
        }
      ],
      "assertion": "present",
      "visit_state": "active",
      "linked_problem": null
    },
    {
      "cap_id": "CAP19",
      "cap_type": "ExamFinding",
      "content_source": "clinician",
      "modality": "assessment",
      "canonical_concept": "knee redness",
      "verification_status": "confirmed",
      "clinical_status": "active",
      "temporality": "current",
      "proposition_text": "The patient exhibits redness in the right knee.",
      "evidence": [
        {
          "turn_id": "S22",
          "turn_speaker": "note",
          "span_text": "Right knee MCL strain.",
          "char_start": 0,
          "char_end": 22
        }
      ],
      "assertion": "present",
      "visit_state": "active",
      "linked_problem": null
    },
    {
      "cap_id": "CAP20",
      "cap_type": "MedicationRequest",
      "content_source": "clinician",
      "modality": "plan",
      "canonical_concept": "Norvasc",
      "verification_status": "confirmed",
      "clinical_status": "active",
      "temporality": "current",
      "proposition_text": "The clinician increases Norvasc to 5 mg daily.",
      "evidence": [
        {
          "turn_id": "S28",
          "turn_speaker": "note",
          "span_text": "For his hypertension, we are going to increase his Norvasc to 5 mg daily as his blood pressures have been elevated. We discussed our goal is for him to get closer to the 120/80 range.",
          "char_start": 0,
          "char_end": 183
        }
      ],
      "assertion": "present",
      "visit_state": "active",
      "linked_problem": null
    },
    {
      "cap_id": "CAP21",
      "cap_type": "MedicationRequest",
      "content_source": "clinician",
      "modality": "plan",
      "canonical_concept": "meloxicam",
      "verification_status": "confirmed",
      "clinical_status": "active",
      "temporality": "current",
      "proposition_text": "The clinician prescribes meloxicam 15 mg.",
      "evidence": [
        {
          "turn_id": "S26",
          "turn_speaker": "note",
          "span_text": "After reviewing the patient's examination and radiographic findings today, I had a lengthy discussion with the patient in regards to his current symptoms. I have recommended that we obtain an MRI of the right knee to further evaluate for a possible MCL tear. In the meantime, he will continue with Tylenol for pain relief. I have also prescribed him meloxicam 15 mg for pain and swelling. He will be placed into a knee immobilizer and has been advised to remain non weight-bearing for the next couple of weeks.",
          "char_start": 0,
          "char_end": 510
        }
      ],
      "assertion": "present",
      "visit_state": "active",
      "linked_problem": null
    },
    {
      "cap_id": "CAP22",
      "cap_type": "MedicationStatement",
      "content_source": "clinician",
      "modality": "assessment",
      "canonical_concept": "Norvasc",
      "verification_status": "confirmed",
      "clinical_status": "active",
      "temporality": "current",
      "proposition_text": "The patient is taking Norvasc 5 mg daily.",
      "evidence": [
        {
          "turn_id": "S4",
          "turn_speaker": "note",
          "span_text": "The patient has a history of hypertension and diabetes. He reports that he does not check is blood pressure at home very often, but he typically runs 140 to 150 range over 80. He is taking 5 mg of Norvasc daily. In terms of his diet, he states that he enjoys eating whatever he likes. His most recent A1C was 7.2. He is taking metformin 500 mg daily, however there are days where he skips this because of gastrointestinal upset. He denies checking his blood sugar at home consistently and that when he does check he has been around 150.",
          "char_start": 0,
          "char_end": 536
        }
      ],
      "assertion": "present",
      "visit_state": "active",
      "linked_problem": null
    },
    {
      "cap_id": "CAP23",
      "cap_type": "MedicationStatement",
      "content_source": "clinician",
      "modality": "assessment",
      "canonical_concept": "Metformin",
      "verification_status": "confirmed",
      "clinical_status": "active",
      "temporality": "current",
      "proposition_text": "The patient is taking Metformin 500 mg daily.",
      "evidence": [
        {
          "turn_id": "S4",
          "turn_speaker": "note",
          "span_text": "The patient has a history of hypertension and diabetes. He reports that he does not check is blood pressure at home very often, but he typically runs 140 to 150 range over 80. He is taking 5 mg of Norvasc daily. In terms of his diet, he states that he enjoys eating whatever he likes. His most recent A1C was 7.2. He is taking metformin 500 mg daily, however there are days where he skips this because of gastrointestinal upset. He denies checking his blood sugar at home consistently and that when he does check he has been around 150.",
          "char_start": 0,
          "char_end": 536
        }
      ],
      "assertion": "present",
      "visit_state": "active",
      "linked_problem": null
    }
  ],
  "filtered_nonverifiable_units": [],
  "chunk_count": 4,
  "extraction_mode": "single_call",
  "runtime_seconds": 106.364
}
